{
    "page": {
        "font-size": "10",
        "orientation": "P",
        "columns": "1",
        "unit": "mm",
        "size": [
            "215.9",
            "279.4"
        ],
        "margin-top": "1.6",
        "margin-left": "1.6",
        "margin-right": "1.6",
        "margin-bottom": "1.6",
        "margin-header": "0.0",
        "margin-footer": "0.0"
    },
    "tag": {
        "width": "212.7",
        "height": "138.1",
        "border": "0",
        "margin-left": "14.01"
    }
}